auroraplot-0.2.0.dist-info/DESCRIPTION.rst
auroraplot-0.2.0.dist-info/metadata.json
auroraplot-0.2.0.dist-info/METADATA
auroraplot-0.2.0.dist-info/top_level.txt
auroraplot-0.2.0.dist-info/WHEEL
auroraplot-0.2.0.dist-info/RECORD
auroraplot/humiditydata.py
auroraplot/data.py
auroraplot/voltagedata.py
auroraplot/mytest.py
auroraplot/magdata.py
auroraplot/dt64tools.py
auroraplot/tools.py
auroraplot/data_temp.py
auroraplot/__init__.py
auroraplot/filter.py
auroraplot/temperaturedata.py
auroraplot/auroralactivity.py
auroraplot/datasets/cloudwatch.py
auroraplot/datasets/dtu.py
auroraplot/datasets/aurorawatchnet.py
auroraplot/datasets/sam.py
auroraplot/datasets/__init__.py
auroraplot/datasets/uit.py
auroraplot/datasets/samnet.py
