Metadata-Version: 2.0
Name: auroraplot
Version: 0.2.0
Summary: Analyse and plot space weather datasets.
Home-page: https://github.com/stevemarple/auroraplot
Author: Steve Marple
Author-email: s.marple@lancaster.ac.uk
License: PSF
Platform: UNKNOWN
Classifier: Development Status :: 4 - Beta
Classifier: Intended Audience :: Education
Classifier: Intended Audience :: Science/Research
Classifier: Natural Language :: English
Classifier: License :: OSI Approved :: Python Software Foundation License
Classifier: Operating System :: OS Independent
Classifier: Programming Language :: Python
Classifier: Programming Language :: Python :: 2
Classifier: Programming Language :: Python :: 2.7
Classifier: Programming Language :: Python :: 3
Classifier: Programming Language :: Python :: 3.3
Classifier: Topic :: Software Development :: Libraries :: Python Modules
Requires-Dist: matplotlib
Requires-Dist: numpy (>=1.7)
Requires-Dist: scipy
